openpnm/__init__.py
openpnm/version.py
openpnm/algorithms/AdvectionDiffusion.py
openpnm/algorithms/FickianDiffusion.py
openpnm/algorithms/FourierConduction.py
openpnm/algorithms/GenericAlgorithm.py
openpnm/algorithms/GenericTransport.py
openpnm/algorithms/InvasionPercolation.py
openpnm/algorithms/IonicConduction.py
openpnm/algorithms/MixedInvasionPercolation.py
openpnm/algorithms/MixedInvasionPercolationCoop.py
openpnm/algorithms/NernstPlanck.py
openpnm/algorithms/NernstPlanckMultiphysics.py
openpnm/algorithms/NonNewtonianStokesFlow.py
openpnm/algorithms/OhmicConduction.py
openpnm/algorithms/OrdinaryPercolation.py
openpnm/algorithms/Porosimetry.py
openpnm/algorithms/ReactiveTransport.py
openpnm/algorithms/StokesFlow.py
openpnm/algorithms/TransientAdvectionDiffusion.py
openpnm/algorithms/TransientFickianDiffusion.py
openpnm/algorithms/TransientIonicConduction.py
openpnm/algorithms/TransientNernstPlanck.py
openpnm/algorithms/TransientNernstPlanckMultiphysics.py
openpnm/algorithms/TransientReactiveTransport.py
openpnm/algorithms/__init__.py
openpnm/algorithms/metrics/FormationFactor.py
openpnm/algorithms/metrics/GenericMetric.py
openpnm/algorithms/metrics/MercuryIntrusion.py
openpnm/algorithms/metrics/RelativePermeability.py
openpnm/algorithms/metrics/__init__.py
openpnm/core/Base.py
openpnm/core/ModelsMixin.py
openpnm/core/Subdomain.py
openpnm/core/__init__.py
openpnm/geometry/Boundary.py
openpnm/geometry/Boundary_2D.py
openpnm/geometry/GenericGeometry.py
openpnm/geometry/Imported.py
openpnm/geometry/StickAndBall.py
openpnm/geometry/StickAndBall_2D.py
openpnm/geometry/__init__.py
openpnm/io/COMSOL.py
openpnm/io/CSV.py
openpnm/io/Dict.py
openpnm/io/GenericIO.py
openpnm/io/HDF5.py
openpnm/io/JSONGraphFormat.py
openpnm/io/MARock.py
openpnm/io/MAT.py
openpnm/io/NetworkX.py
openpnm/io/OpenpnmIO.py
openpnm/io/Pandas.py
openpnm/io/PerGeos.py
openpnm/io/PoreSpy.py
openpnm/io/STL.py
openpnm/io/Salome.py
openpnm/io/Statoil.py
openpnm/io/VTK.py
openpnm/io/XDMF.py
openpnm_test-3.0.0.dist-info/LICENSE
openpnm_test-3.0.0.dist-info/METADATA
openpnm_test-3.0.0.dist-info/WHEEL
openpnm_test-3.0.0.dist-info/top_level.txt
openpnm_test-3.0.0.dist-info/RECORD
