Metadata-Version: 2.1
Name: openpnm-test
Version: 3.0.0
Summary: A framework for conducting pore network modeling simulations of multiphase transport in porous materials
Home-page: http://openpnm.org
Author: OpenPNM Team
Author-email: jgostick@uwaterloo.ca
License: UNKNOWN
Download-URL: https://github.com/pmeal/OpenPNM/
Project-URL: Documentation, https://openpnm.readthedocs.io/en/master/
Project-URL: Source, https://github.com/PMEAL/OpenPNM
Project-URL: Tracker, https://github.com/PMEAL/OpenPNM/issues
Platform: UNKNOWN
Classifier: Development Status :: 5 - Production/Stable
Classifier: License :: OSI Approved :: MIT License
Classifier: Programming Language :: Python
Classifier: Topic :: Scientific/Engineering
Classifier: Topic :: Scientific/Engineering :: Physics
Requires-Python: >= 3.6
Requires-Dist: numpy (>=1.15)
Requires-Dist: scipy (>=1.1)
Requires-Dist: scikit-image (>=0.14)
Requires-Dist: networkx (>=2)
Requires-Dist: h5py (>=2.8)
Requires-Dist: sympy
Requires-Dist: matplotlib
Requires-Dist: pandas
Requires-Dist: numba
Requires-Dist: transforms3d
Requires-Dist: flatdict
Requires-Dist: gitpython
Requires-Dist: jsonschema
Requires-Dist: unyt
Requires-Dist: terminaltables
Requires-Dist: docrep
